MDSTimeManager/__init__.py
MDSTimeManager/setup/__init__.py
MDSTimeManager/setup/course.py
MDSTimeManager/setup/mdstmerror.py
MDSTimeManager/setup/person.py
MDSTimeManager/system/TimeManager.py
MDSTimeManager/system/__init__.py
MDSTimeManager/system/deliverableviewer.py
MDSTimeManager/system/main.py
MDSTimeManager-1.4.dist-info/LICENSE.txt
MDSTimeManager-1.4.dist-info/METADATA
MDSTimeManager-1.4.dist-info/WHEEL
MDSTimeManager-1.4.dist-info/top_level.txt
MDSTimeManager-1.4.dist-info/RECORD
