Metadata-Version: 2.1
Name: MDSTimeManager
Version: 1.4
Summary: MDSTimeManager python package
Home-page: https://github.com/a-foote/MDS_TimeManager
Author: A.Foote, V.Singh
Author-email: alyssa.k.foote@gmail.com
License: MIT
License-File: LICENSE.txt
